opt_generators-0.1.2.dist-info/METADATA
opt_generators-0.1.2.dist-info/WHEEL
opt_generators-0.1.2.dist-info/licenses/LICENSE
opt_generators/__init__.py
opt_generators/opt_generators.cp312-win_amd64.pyd
opt_generators-0.1.2.dist-info/RECORD
